aws_mfa_util/__init__.py
aws_mfa_util/credential.py
aws_mfa_util/util.py
tests/__init__.py
tests/test_main.py
aws_mfa_util-0.1.0.dist-info/LICENSE
aws_mfa_util-0.1.0.dist-info/METADATA
aws_mfa_util-0.1.0.dist-info/WHEEL
aws_mfa_util-0.1.0.dist-info/entry_points.txt
aws_mfa_util-0.1.0.dist-info/top_level.txt
aws_mfa_util-0.1.0.dist-info/RECORD
