Metadata-Version: 2.1
Name: aws-mfa-util
Version: 0.1.0
Summary: AWS CLIにMFA適用アカウントを作成・更新するためのツール
Home-page: https://github.com/papi-tokei/aws-mfa-util
Author: hiroya akita
Author-email: akky.develop@gmail.com
License: MIT
Platform: UNKNOWN
Classifier: Programming Language :: Python :: 3
Classifier: License :: OSI Approved :: MIT License
Requires-Python: >=3.6
Requires-Dist: boto3
Requires-Dist: PyInquirer
